Serialization/__init__.py
Serialization/base_serializer.py
Serialization/dict_serializer.py
Serialization/json_serializer.py
Serialization/serializers_factory.py
Serialization/type_constants.py
Serialization/xml_serializer.py
HandsomeSerialization-0.1.1.dist-info/METADATA
HandsomeSerialization-0.1.1.dist-info/WHEEL
HandsomeSerialization-0.1.1.dist-info/top_level.txt
HandsomeSerialization-0.1.1.dist-info/RECORD
